{
  "verses": [
    {
      "verse_num": 1,
      "segments": [
        {
          "type": "divine",
          "text": "When Israel was a child, I loved him, and out of Egypt I called my son.",
          "speaker": "God"
        }
      ],
      "footnotes": [],
      "references": []
    },
    {
      "verse_num": 2,
      "segments": [
        {
          "type": "narrative",
          "text": "But the more they were called, the more they went away from me."
        },
        {
          "type": "narrative",
          "text": "They sacrificed to the Baals and they burned incense to images."
        }
      ],
      "footnotes": [],
      "references": []
    },
    {
      "verse_num": 3,
      "segments": [
        {
          "type": "divine",
          "text": "It was I who taught Ephraim to walk, taking them by the arms; but they did not realize it was I who healed them.",
          "speaker": "God"
        }
      ],
      "footnotes": [],
      "references": []
    },
    {
      "verse_num": 4,
      "segments": [
        {
          "type": "divine",
          "text": "I led them with cords of human kindness, with ties of love. To them I was like one who lifts a little child to the cheek, and I bent down to feed them.",
          "speaker": "God"
        }
      ],
      "footnotes": [],
      "references": []
    },
    {
      "verse_num": 5,
      "segments": [
        {
          "type": "divine",
          "text": "Will they not return to Egypt and will not Assyria rule over them because they refuse to repent?",
          "speaker": "God"
        }
      ],
      "footnotes": [],
      "references": []
    },
    {
      "verse_num": 6,
      "segments": [
        {
          "type": "narrative",
          "text": "A sword will flash in their cities; it will devour their false prophets and put an end to their plans."
        }
      ],
      "footnotes": [],
      "references": []
    },
    {
      "verse_num": 7,
      "segments": [
        {
          "type": "divine",
          "text": "My people are determined to turn from me. Even though they call me God Most High, I will by no means exalt them.",
          "speaker": "God"
        }
      ],
      "footnotes": [],
      "references": []
    },
    {
      "verse_num": 8,
      "segments": [
        {
          "type": "divine",
          "text": "How can I give you up, Ephraim? How can I hand you over, Israel? How can I treat you like Admah? How can I make you like Zeboyim? My heart is changed within me; all my compassion is aroused.",
          "speaker": "God"
        }
      ],
      "footnotes": [],
      "references": []
    },
    {
      "verse_num": 9,
      "segments": [
        {
          "type": "divine",
          "text": "I will not carry out my fierce anger, nor will I devastate Ephraim again. For I am God, and not a man— the Holy One among you. I will not come against their cities.",
          "speaker": "God"
        }
      ],
      "footnotes": [],
      "references": []
    },
    {
      "verse_num": 10,
      "segments": [
        {
          "type": "narrative",
          "text": "They will follow the Lord; he will roar like a lion."
        },
        {
          "type": "narrative",
          "text": "When he roars, his children will come trembling from the west."
        }
      ],
      "footnotes": [],
      "references": []
    },
    {
      "verse_num": 11,
      "segments": [
        {
          "type": "narrative",
          "text": "They will come from Egypt, trembling like sparrows, from Assyria, fluttering like doves."
        },
        {
          "type": "divine",
          "text": "I will settle them in their homes",
          "speaker": "The Lord"
        }
      ],
      "title": "Israel's Sin",
      "footnotes": [],
      "references": []
    },
    {
      "verse_num": 12,
      "segments": [
        {
          "type": "narrative",
          "text": "Ephraim has surrounded me with lies, Israel with deceit. And Judah is unruly against God, even against the faithful Holy One."
        }
      ],
      "footnotes": [],
      "references": []
    }
  ]
}