{
  "verses": [
    {
      "verse_num": "1",
      "segments": [
        {
          "type": "narrative",
          "text": "The beginning of the Good News of Jesus Christ, the Son of God."
        }
      ],
      "footnotes": [],
      "references": []
    },
    {
      "verse_num": "2",
      "segments": [
        {
          "type": "narrative",
          "text": "As it is written in the prophets,\n"
        },
        {
          "type": "divine",
          "text": "Behold,  I send my messenger before your face, who will prepare your way before you:",
          "speaker": "God"
        }
      ],
      "footnotes": [
        {
          "text": "+ 'Behold , from  'ἰδοὺ, means look at, take notice, observe, see, or gaze at. It is often used as an interjection."
        }
      ],
      "references": []
    },
    {
      "verse_num": "3",
      "segments": [
        {
          "type": "prophetic",
          "text": "the voice of one crying in the wilderness,‘Make ready the way of the Lord! \nMake his paths straight!’",
          "speaker": "Unknown"
        }
      ],
      "footnotes": [],
      "references": []
    },
    {
      "verse_num": "4",
      "segments": [
        {
          "type": "narrative",
          "text": "John came baptizing in the wilderness and preaching the baptism of repentance for forgiveness of sins."
        }
      ],
      "footnotes": [
        {
          "text": "+ or, immersing"
        }
      ],
      "references": []
    },
    {
      "verse_num": "5",
      "segments": [
        {
          "type": "narrative",
          "text": "All the country of Judea and all those of Jerusalem went out to him. They were baptized by him in the Jordan river, confessing their sins."
        }
      ],
      "footnotes": [],
      "references": []
    },
    {
      "verse_num": "6",
      "segments": [
        {
          "type": "narrative",
          "text": "John was clothed with camel’s hair and a leather belt around his waist. He ate locusts and wild honey."
        }
      ],
      "footnotes": [],
      "references": []
    },
    {
      "verse_num": "7",
      "segments": [
        {
          "type": "narrative",
          "text": "He preached, saying, "
        },
        {
          "type": "speech",
          "text": "After me comes he who is mightier than I, the strap of whose sandals I am not worthy to stoop down and loosen.",
          "speaker": "John"
        }
      ],
      "footnotes": [],
      "references": []
    },
    {
      "verse_num": "8",
      "segments": [
        {
          "type": "speech",
          "text": "I baptized you in water, but he will baptize you in the Holy Spirit.",
          "speaker": "John"
        }
      ],
      "footnotes": [
        {
          "text": "+ The Greek word (en) translated here as 'in  could also be translated as  'with in some contexts."
        }
      ],
      "references": []
    },
    {
      "verse_num": "9",
      "segments": [
        {
          "type": "narrative",
          "text": "In those days, Jesus came from Nazareth of Galilee, and was baptized by John in the Jordan."
        }
      ],
      "footnotes": [],
      "references": []
    },
    {
      "verse_num": "10",
      "segments": [
        {
          "type": "narrative",
          "text": "Immediately coming up from the water, he saw the heavens parting and the Spirit descending on him like a dove."
        }
      ],
      "footnotes": [],
      "references": []
    },
    {
      "verse_num": "11",
      "segments": [
        {
          "type": "narrative",
          "text": "A voice came out of the sky, "
        },
        {
          "type": "divine",
          "text": "You are my beloved Son, in whom I am well pleased.",
          "speaker": "God"
        }
      ],
      "footnotes": [],
      "references": []
    },
    {
      "verse_num": "12",
      "segments": [
        {
          "type": "narrative",
          "text": "Immediately the Spirit drove him out into the wilderness."
        }
      ],
      "footnotes": [],
      "references": []
    },
    {
      "verse_num": "13",
      "segments": [
        {
          "type": "narrative",
          "text": "He was there in the wilderness forty days, tempted by Satan. He was with the wild animals; and the angels were serving him."
        }
      ],
      "footnotes": [],
      "references": []
    },
    {
      "verse_num": "14",
      "segments": [
        {
          "type": "narrative",
          "text": "Now after John was taken into custody, Jesus came into Galilee, preaching the Good News of God’s Kingdom,"
        }
      ],
      "footnotes": [],
      "references": []
    },
    {
      "verse_num": "15",
      "segments": [
        {
          "type": "narrative",
          "text": "and saying,\n"
        },
        {
          "type": "sermon",
          "text": "The time is fulfilled, and God’s Kingdom is at hand! Repent, and believe in the Good News.",
          "speaker": "Jesus"
        }
      ],
      "footnotes": [],
      "references": []
    },
    {
      "verse_num": "16",
      "segments": [
        {
          "type": "narrative",
          "text": "Passing along by the sea of Galilee, he saw Simon and Andrew, the brother of Simon, casting a net into the sea, for they were fishermen."
        }
      ],
      "footnotes": [],
      "references": []
    },
    {
      "verse_num": "17",
      "segments": [
        {
          "type": "narrative",
          "text": "Jesus said to them,\n"
        },
        {
          "type": "divine",
          "text": "Come after me, and I will make you into fishers for men.",
          "speaker": "Jesus"
        }
      ],
      "footnotes": [],
      "references": []
    },
    {
      "verse_num": "18",
      "segments": [
        {
          "type": "narrative",
          "text": "Immediately they left their nets, and followed him."
        }
      ],
      "footnotes": [],
      "references": []
    },
    {
      "verse_num": "19",
      "segments": [
        {
          "type": "narrative",
          "text": "Going on a little further from there, he saw James the son of Zebedee, and John his brother, who were also in the boat mending the nets."
        }
      ],
      "footnotes": [],
      "references": []
    },
    {
      "verse_num": "20",
      "segments": [
        {
          "type": "narrative",
          "text": "Immediately he called them, and they left their father, Zebedee, in the boat with the hired servants, and went after him."
        }
      ],
      "footnotes": [],
      "references": []
    },
    {
      "verse_num": "21",
      "segments": [
        {
          "type": "law",
          "text": "They went into Capernaum, and immediately on the Sabbath day he entered into the synagogue and taught."
        }
      ],
      "footnotes": [],
      "references": []
    },
    {
      "verse_num": "22",
      "segments": [
        {
          "type": "narrative",
          "text": "They were astonished at his teaching, for he taught them as having authority, and not as the scribes."
        }
      ],
      "footnotes": [],
      "references": []
    },
    {
      "verse_num": "23",
      "segments": [
        {
          "type": "law",
          "text": "Immediately there was in their synagogue a man with an unclean spirit, and he cried out,"
        }
      ],
      "footnotes": [],
      "references": []
    },
    {
      "verse_num": "24",
      "segments": [
        {
          "type": "narrative",
          "text": "saying, "
        },
        {
          "type": "divine",
          "text": "Ha! What do we have to do with you, Jesus, you Nazarene? Have you come to destroy us? I know who you are: the Holy One of God!",
          "speaker": "Jesus"
        }
      ],
      "footnotes": [],
      "references": []
    },
    {
      "verse_num": "25",
      "segments": [
        {
          "type": "narrative",
          "text": "Jesus rebuked him, saying,\n"
        },
        {
          "type": "divine",
          "text": "Be quiet, and come out of him!",
          "speaker": "Jesus"
        }
      ],
      "footnotes": [],
      "references": []
    },
    {
      "verse_num": "26",
      "segments": [
        {
          "type": "law",
          "text": "The unclean spirit, convulsing him and crying with a loud voice, came out of him."
        }
      ],
      "footnotes": [],
      "references": []
    },
    {
      "verse_num": "27",
      "segments": [
        {
          "type": "narrative",
          "text": "They were all amazed, so that they questioned among themselves, saying, "
        },
        {
          "type": "divine",
          "text": "What is this? A new teaching? For with authority he commands even the unclean spirits, and they obey him!",
          "speaker": "Crowd"
        }
      ],
      "footnotes": [],
      "references": []
    },
    {
      "verse_num": "28",
      "segments": [
        {
          "type": "narrative",
          "text": "The report of him went out immediately everywhere into all the region of Galilee and its surrounding area."
        }
      ],
      "footnotes": [],
      "references": []
    },
    {
      "verse_num": "29",
      "segments": [
        {
          "type": "narrative",
          "text": "Immediately, when they had come out of the synagogue, they came into the house of Simon and Andrew, with James and John."
        }
      ],
      "footnotes": [],
      "references": []
    },
    {
      "verse_num": "30",
      "segments": [
        {
          "type": "narrative",
          "text": "Now Simon’s wife’s mother lay sick with a fever, and immediately they told him about her."
        }
      ],
      "footnotes": [],
      "references": []
    },
    {
      "verse_num": "31",
      "segments": [
        {
          "type": "narrative",
          "text": "He came and took her by the hand and raised her up. The fever left her immediately,  and she served them."
        }
      ],
      "footnotes": [
        {
          "text": "+ NU omits 'immediately."
        }
      ],
      "references": []
    },
    {
      "verse_num": "32",
      "segments": [
        {
          "type": "narrative",
          "text": "At evening, when the sun had set, they brought to him all who were sick and those who were possessed by demons."
        }
      ],
      "footnotes": [],
      "references": []
    },
    {
      "verse_num": "33",
      "segments": [
        {
          "type": "narrative",
          "text": "All the city was gathered together at the door."
        }
      ],
      "footnotes": [],
      "references": []
    },
    {
      "verse_num": "34",
      "segments": [
        {
          "type": "narrative",
          "text": "He healed many who were sick with various diseases and cast out many demons. He didn’t allow the demons to speak, because they knew him."
        }
      ],
      "footnotes": [],
      "references": []
    },
    {
      "verse_num": "35",
      "segments": [
        {
          "type": "narrative",
          "text": "Early in the morning, while it was still dark, he rose up and went out, and departed into a deserted place, and prayed there."
        }
      ],
      "footnotes": [],
      "references": []
    },
    {
      "verse_num": "36",
      "segments": [
        {
          "type": "narrative",
          "text": "Simon and those who were with him searched for him."
        }
      ],
      "footnotes": [],
      "references": []
    },
    {
      "verse_num": "37",
      "segments": [
        {
          "type": "narrative",
          "text": "They found him and told him, "
        },
        {
          "type": "divine",
          "text": "Everyone is looking for you.",
          "speaker": "Simon"
        }
      ],
      "footnotes": [],
      "references": []
    },
    {
      "verse_num": "38",
      "segments": [
        {
          "type": "narrative",
          "text": "He said to them,\n"
        },
        {
          "type": "divine",
          "text": "Let’s go elsewhere into the next towns, that I may preach there also, because I came out for this reason.",
          "speaker": "Jesus"
        }
      ],
      "footnotes": [],
      "references": []
    },
    {
      "verse_num": "39",
      "segments": [
        {
          "type": "narrative",
          "text": "He went into their synagogues throughout all Galilee, preaching and casting out demons."
        }
      ],
      "footnotes": [],
      "references": []
    },
    {
      "verse_num": "40",
      "segments": [
        {
          "type": "narrative",
          "text": "A leper came to him, begging him, kneeling down to him, and saying to him, "
        },
        {
          "type": "divine",
          "text": "If you want to, you can make me clean.",
          "speaker": "Jesus"
        }
      ],
      "footnotes": [],
      "references": []
    },
    {
      "verse_num": "41",
      "segments": [
        {
          "type": "narrative",
          "text": "Being moved with compassion, he stretched out his hand, and touched him, and said to him,\n"
        },
        {
          "type": "divine",
          "text": "I want to. Be made clean.",
          "speaker": "Jesus"
        }
      ],
      "footnotes": [],
      "references": []
    },
    {
      "verse_num": "42",
      "segments": [
        {
          "type": "law",
          "text": "When he had said this, immediately the leprosy departed from him and he was made clean."
        }
      ],
      "footnotes": [],
      "references": []
    },
    {
      "verse_num": "43",
      "segments": [
        {
          "type": "narrative",
          "text": "He strictly warned him and immediately sent him out,"
        }
      ],
      "footnotes": [],
      "references": []
    },
    {
      "verse_num": "44",
      "segments": [
        {
          "type": "narrative",
          "text": "and said to him,\n"
        },
        {
          "type": "divine",
          "text": "See that you say nothing to anybody, but go show yourself to the priest and offer for your cleansing the things which Moses commanded, for a testimony to them.",
          "speaker": "Jesus"
        }
      ],
      "footnotes": [],
      "references": []
    },
    {
      "verse_num": "45",
      "segments": [
        {
          "type": "narrative",
          "text": "But he went out, and began to proclaim it much, and to spread about the matter, so that Jesus could no more openly enter into a city, but was outside in desert places. People came to him from everywhere."
        }
      ],
      "footnotes": [],
      "references": []
    }
  ]
}