{
  "verses": [
    {
      "verse_num": "1",
      "segments": [
        {
          "type": "hymnal",
          "text": "Unless Yahweh builds the house, they who build it labor in vain. Unless Yahweh watches over the city, the watchman guards it in vain."
        }
      ],
      "footnotes": [],
      "references": []
    },
    {
      "verse_num": "2",
      "segments": [
        {
          "type": "hymnal",
          "text": "It is vain for you to rise up early, to stay up late,"
        },
        {
          "type": "hymnal",
          "text": "eating the bread of toil,\nfor he gives sleep to his loved ones."
        }
      ],
      "footnotes": [],
      "references": []
    },
    {
      "verse_num": "3",
      "segments": [
        {
          "type": "hymnal",
          "text": "Behold, children are a heritage of Yahweh. The fruit of the womb is his reward."
        }
      ],
      "footnotes": [],
      "references": []
    },
    {
      "verse_num": "4",
      "segments": [
        {
          "type": "hymnal",
          "text": "As arrows in the hand of a mighty man, so are the children of youth."
        }
      ],
      "footnotes": [],
      "references": []
    },
    {
      "verse_num": "5",
      "segments": [
        {
          "type": "hymnal",
          "text": "Happy is the man who has his quiver full of them. They won’t be disappointed when they speak with their enemies in the gate."
        }
      ],
      "footnotes": [],
      "references": []
    }
  ]
}