{
  "verses": [
    {
      "verse_num": 1,
      "segments": [
        {
          "type": "narrative",
          "text": "My God, my God, why have you forsaken me?"
        },
        {
          "type": "divine",
          "text": "Why are you so far from saving me, so far from my cries of anguish?",
          "speaker": "David"
        }
      ],
      "footnotes": [
        "Aijeleth…: or, the hind of the morning",
        "helping…: Heb. my salvation"
      ],
      "references": [],
      "heading": []
    },
    {
      "verse_num": 2,
      "segments": [
        {
          "type": "narrative",
          "text": "I cry out by day, but you do not answer,"
        },
        {
          "type": "divine",
          "text": "by night, but I find no rest.",
          "speaker": "David"
        }
      ],
      "footnotes": [
        "am…: Heb. there is no silence to me"
      ],
      "references": [],
      "heading": []
    },
    {
      "verse_num": 3,
      "segments": [
        {
          "type": "narrative",
          "text": "Yet you are enthroned as the Holy One;"
        },
        {
          "type": "divine",
          "text": "you are the one Israel praises.",
          "speaker": "David"
        }
      ],
      "footnotes": [],
      "references": [],
      "heading": []
    },
    {
      "verse_num": 4,
      "segments": [
        {
          "type": "narrative",
          "text": "In you our ancestors put their trust;"
        },
        {
          "type": "divine",
          "text": "they trusted and you delivered them.",
          "speaker": "David"
        }
      ],
      "footnotes": [],
      "references": [],
      "heading": []
    },
    {
      "verse_num": 5,
      "segments": [
        {
          "type": "narrative",
          "text": "To you they cried out and were saved;"
        },
        {
          "type": "divine",
          "text": "in you they trusted and were not put to shame.",
          "speaker": "David"
        }
      ],
      "footnotes": [],
      "references": [],
      "heading": []
    },
    {
      "verse_num": 6,
      "segments": [
        {
          "type": "narrative",
          "text": "But I am a worm and not a man,"
        },
        {
          "type": "divine",
          "text": "scorned by everyone, despised by the people.",
          "speaker": "David"
        }
      ],
      "footnotes": [],
      "references": [],
      "heading": []
    },
    {
      "verse_num": 7,
      "segments": [
        {
          "type": "narrative",
          "text": "All who see me mock me;"
        },
        {
          "type": "divine",
          "text": "they hurl insults, shaking their heads.",
          "speaker": "David"
        }
      ],
      "footnotes": [
        "shoot…: Heb. open"
      ],
      "references": [],
      "heading": []
    },
    {
      "verse_num": 8,
      "segments": [
        {
          "type": "narrative",
          "text": "They say, 'He trusts in the LORD.'"
        },
        {
          "type": "divine",
          "text": "'Let the LORD rescue him. Let him deliver him, since he delights in him.'",
          "speaker": "David"
        }
      ],
      "footnotes": [
        "He trusted…: Heb. He rolled himself on",
        "seeing…: or, if he delight in"
      ],
      "references": [],
      "heading": []
    },
    {
      "verse_num": 9,
      "segments": [
        {
          "type": "narrative",
          "text": "Yet you brought me out of the womb;"
        },
        {
          "type": "divine",
          "text": "you made me trust in you, even at my mother’s breast.",
          "speaker": "David"
        }
      ],
      "footnotes": [
        "didst…: or, kept me in safety"
      ],
      "references": [],
      "heading": []
    },
    {
      "verse_num": 10,
      "segments": [
        {
          "type": "narrative",
          "text": "From birth I was cast on you;"
        },
        {
          "type": "divine",
          "text": "from my mother’s womb you have been my God.",
          "speaker": "David"
        }
      ],
      "footnotes": [],
      "references": [],
      "heading": []
    },
    {
      "verse_num": 11,
      "segments": [
        {
          "type": "narrative",
          "text": "Do not be far from me, for trouble is near"
        },
        {
          "type": "divine",
          "text": "and there is no one to help.",
          "speaker": "David"
        }
      ],
      "footnotes": [
        "none…: Heb. not a helper"
      ],
      "references": [],
      "heading": []
    },
    {
      "verse_num": 12,
      "segments": [
        {
          "type": "narrative",
          "text": "Many bulls surround me;"
        },
        {
          "type": "divine",
          "text": "strong bulls of Bashan encircle me.",
          "speaker": "David"
        }
      ],
      "footnotes": [],
      "references": [],
      "heading": []
    },
    {
      "verse_num": 13,
      "segments": [
        {
          "type": "narrative",
          "text": "Roaring lions that tear their prey open their mouths wide against me."
        }
      ],
      "footnotes": [
        "gaped…: Heb. opened their mouths against me"
      ],
      "references": [],
      "heading": []
    },
    {
      "verse_num": 14,
      "segments": [
        {
          "type": "narrative",
          "text": "I am poured out like water,"
        },
        {
          "type": "divine",
          "text": "and all my bones are out of joint.",
          "speaker": "David"
        }
      ],
      "footnotes": [
        "out of…: or, sundered"
      ],
      "references": [],
      "heading": []
    },
    {
      "verse_num": 15,
      "segments": [
        {
          "type": "narrative",
          "text": "My heart has turned to wax;"
        },
        {
          "type": "divine",
          "text": "it has melted within me.",
          "speaker": "David"
        }
      ],
      "footnotes": [],
      "references": [],
      "heading": []
    },
    {
      "verse_num": 16,
      "segments": [
        {
          "type": "narrative",
          "text": "My mouth is dried up like a potsherd,"
        },
        {
          "type": "divine",
          "text": "and my tongue sticks to the roof of my mouth;",
          "speaker": "David"
        }
      ],
      "footnotes": [],
      "references": [],
      "heading": []
    },
    {
      "verse_num": 17,
      "segments": [
        {
          "type": "narrative",
          "text": "You lay me in the dust of death."
        }
      ],
      "footnotes": [],
      "references": [],
      "heading": []
    },
    {
      "verse_num": 18,
      "segments": [
        {
          "type": "narrative",
          "text": "Dogs surround me, a pack of villains encircles me;"
        },
        {
          "type": "divine",
          "text": "they pierce my hands and my feet.",
          "speaker": "David"
        }
      ],
      "footnotes": [],
      "references": [],
      "heading": []
    },
    {
      "verse_num": 19,
      "segments": [
        {
          "type": "narrative",
          "text": "All my bones are on display;"
        },
        {
          "type": "divine",
          "text": "people stare and gloat over me.",
          "speaker": "David"
        }
      ],
      "footnotes": [],
      "references": [],
      "heading": []
    },
    {
      "verse_num": 20,
      "segments": [
        {
          "type": "narrative",
          "text": "They divide my clothes among them"
        },
        {
          "type": "divine",
          "text": "and cast lots for my garment.",
          "speaker": "David"
        }
      ],
      "footnotes": [
        "my darling: Heb. my only one",
        "power: Heb. hand"
      ],
      "references": [],
      "heading": []
    },
    {
      "verse_num": 21,
      "segments": [
        {
          "type": "narrative",
          "text": "But you, LORD, do not be far from me."
        },
        {
          "type": "prayer",
          "text": "You are my strength; come quickly to help me.",
          "speaker": "David"
        }
      ],
      "footnotes": [],
      "references": [],
      "heading": []
    },
    {
      "verse_num": 22,
      "segments": [
        {
          "type": "narrative",
          "text": "I will declare your name to my people;"
        },
        {
          "type": "divine",
          "text": "in the assembly I will praise you.",
          "speaker": "David"
        }
      ],
      "footnotes": [],
      "references": [],
      "heading": []
    },
    {
      "verse_num": 23,
      "segments": [
        {
          "type": "narrative",
          "text": "You who fear the LORD, praise him!"
        },
        {
          "type": "divine",
          "text": "All you descendants of Jacob, honor him!",
          "speaker": "David"
        }
      ],
      "footnotes": [],
      "references": [],
      "heading": []
    },
    {
      "verse_num": 24,
      "segments": [
        {
          "type": "narrative",
          "text": "For he has not despised or scorned the suffering of the afflicted one;"
        },
        {
          "type": "divine",
          "text": "he has not hidden his face from him but has listened to his cry for help.",
          "speaker": "David"
        }
      ],
      "footnotes": [],
      "references": [],
      "heading": []
    },
    {
      "verse_num": 25,
      "segments": [
        {
          "type": "narrative",
          "text": "From you comes the theme of my praise in the great assembly;"
        },
        {
          "type": "divine",
          "text": "before those who fear you I will fulfill my vows.",
          "speaker": "David"
        }
      ],
      "footnotes": [],
      "references": [],
      "heading": []
    },
    {
      "verse_num": 26,
      "segments": [
        {
          "type": "narrative",
          "text": "The poor will eat and be satisfied;"
        },
        {
          "type": "divine",
          "text": "those who seek the LORD will praise him—may your hearts live forever!",
          "speaker": "David"
        }
      ],
      "footnotes": [],
      "references": [],
      "heading": []
    },
    {
      "verse_num": 27,
      "segments": [
        {
          "type": "narrative",
          "text": "All the ends of the earth will remember and turn to the LORD,"
        },
        {
          "type": "divine",
          "text": "and all the families of the nations will bow down before him.",
          "speaker": "David"
        }
      ],
      "footnotes": [],
      "references": [],
      "heading": []
    },
    {
      "verse_num": 28,
      "segments": [
        {
          "type": "narrative",
          "text": "For dominion belongs to the LORD"
        },
        {
          "type": "divine",
          "text": "and he rules over the nations.",
          "speaker": "David"
        }
      ],
      "footnotes": [],
      "references": [],
      "heading": []
    },
    {
      "verse_num": 29,
      "segments": [
        {
          "type": "narrative",
          "text": "All the rich of the earth will feast and worship;"
        },
        {
          "type": "divine",
          "text": "all who go down to the dust will kneel before him—those who cannot keep themselves alive.",
          "speaker": "David"
        }
      ],
      "footnotes": [],
      "references": [],
      "heading": []
    },
    {
      "verse_num": 30,
      "segments": [
        {
          "type": "narrative",
          "text": "Posterity will serve him;"
        },
        {
          "type": "divine",
          "text": "future generations will be told about the Lord.",
          "speaker": "David"
        }
      ],
      "footnotes": [],
      "references": [],
      "heading": []
    },
    {
      "verse_num": 31,
      "segments": [
        {
          "type": "narrative",
          "text": "They will proclaim his righteousness, declaring to a people yet unborn:"
        },
        {
          "type": "divine",
          "text": "'He has done it!'.",
          "speaker": "David"
        }
      ],
      "footnotes": [],
      "references": [],
      "heading": []
    }
  ]
}