{
  "verses": [
    {
      "verse_num": "1",
      "segments": [
        {
          "type": "hymnal",
          "text": "Confirm that I'm innocent, Lord, for I have acted with integrity, and I have trusted in the Lord without fail.\n"
        }
      ],
      "footnotes": [],
      "references": []
    },
    {
      "verse_num": "2",
      "segments": [
        {
          "type": "hymnal",
          "text": "Examine me, Lord, test me; investigate my thoughts and intentions."
        }
      ],
      "footnotes": [],
      "references": []
    },
    {
      "verse_num": "3",
      "segments": [
        {
          "type": "hymnal",
          "text": "For I always remember your trustworthy love, and I follow your truth."
        }
      ],
      "footnotes": [],
      "references": []
    },
    {
      "verse_num": "4",
      "segments": [
        {
          "type": "hymnal",
          "text": "I don't join in with liars and I don't associate with hypocrites."
        }
      ],
      "footnotes": [],
      "references": []
    },
    {
      "verse_num": "5",
      "segments": [
        {
          "type": "hymnal",
          "text": "I refuse to get together with those who do evil, and I won't involve myself with the wicked."
        }
      ],
      "footnotes": [],
      "references": []
    },
    {
      "verse_num": "6",
      "segments": [
        {
          "type": "hymnal",
          "text": "I wash my hands to show my innocence. I come to worship at your altar, Lord,"
        }
      ],
      "footnotes": [],
      "references": []
    },
    {
      "verse_num": "7",
      "segments": [
        {
          "type": "hymnal",
          "text": "singing my thanks, telling of all the wonderful things you have done."
        }
      ],
      "footnotes": [],
      "references": []
    },
    {
      "verse_num": "8",
      "segments": [
        {
          "type": "hymnal",
          "text": "Lord, I love your house, the place where you live in your glory."
        }
      ],
      "footnotes": [],
      "references": []
    },
    {
      "verse_num": "9",
      "segments": [
        {
          "type": "hymnal",
          "text": "Please don't sweep me away along with sinners. Don't include me with those who commit murder,"
        }
      ],
      "footnotes": [],
      "references": []
    },
    {
      "verse_num": "10",
      "segments": [
        {
          "type": "hymnal",
          "text": "whose hands carry out their evil schemes and grab hold of bribes."
        }
      ],
      "footnotes": [],
      "references": []
    },
    {
      "verse_num": "11",
      "segments": [
        {
          "type": "hymnal",
          "text": "For I don't do that—I act with integrity. Save me and be gracious to me!"
        }
      ],
      "footnotes": [],
      "references": []
    },
    {
      "verse_num": "12",
      "segments": [
        {
          "type": "hymnal",
          "text": "I st and for what's right,  and I will praise the Lord when we meet together to worship him."
        }
      ],
      "footnotes": [],
      "references": []
    }
  ]
}