{
  "verses": [
    {
      "verse_num": "1",
      "segments": [
        {
          "type": "hymnal",
          "text": "I am moved to write about this wonderful subject. Let me share what I have written for the king. What I say comes from the pen of a skilled author.\n"
        }
      ],
      "footnotes": [],
      "references": []
    },
    {
      "verse_num": "2",
      "segments": [
        {
          "type": "hymnal",
          "text": "You are more handsome than anyone else. You always speak graciously, for God has blessed you forever."
        }
      ],
      "footnotes": [],
      "references": []
    },
    {
      "verse_num": "3",
      "segments": [
        {
          "type": "hymnal",
          "text": "Strap on your sword, mighty warrior, stride out in glory and majesty!"
        }
      ],
      "footnotes": [],
      "references": []
    },
    {
      "verse_num": "4",
      "segments": [
        {
          "type": "hymnal",
          "text": "In your majesty ride out to victory, in the defense of truth, humility, and right, because you are strong and act powerfully. "
        }
      ],
      "footnotes": [],
      "references": []
    },
    {
      "verse_num": "5",
      "segments": [
        {
          "type": "hymnal",
          "text": "Your sharp arrows pierce the hearts of your enemies; the nations fall under you."
        }
      ],
      "footnotes": [],
      "references": []
    },
    {
      "verse_num": "6",
      "segments": [
        {
          "type": "hymnal",
          "text": "Your throne comes from God, and lasts forever and ever. The scepter with which you rule is a scepter of fairness."
        }
      ],
      "footnotes": [],
      "references": []
    },
    {
      "verse_num": "7",
      "segments": [
        {
          "type": "hymnal",
          "text": "You love what is right and hate what is wrong. That is why God, your God, has placed you above everyone else by anointing you with the oil of joy."
        }
      ],
      "footnotes": [],
      "references": []
    },
    {
      "verse_num": "8",
      "segments": [
        {
          "type": "hymnal",
          "text": "Your robes are perfumed with aloes, myrrh, and cassia; music played on stringed instruments in palaces decorated with ivory makes you happy."
        }
      ],
      "footnotes": [],
      "references": []
    },
    {
      "verse_num": "9",
      "segments": [
        {
          "type": "hymnal",
          "text": "The daughters of kings are among the noblewomen; the queen stands beside you on your right, wearing jewelry made of gold from Ophir."
        }
      ],
      "footnotes": [],
      "references": []
    },
    {
      "verse_num": "10",
      "segments": [
        {
          "type": "hymnal",
          "text": "Listen to what I have to say, daughter;  please pay attention. Don't pine for your people and your family."
        }
      ],
      "footnotes": [],
      "references": []
    },
    {
      "verse_num": "11",
      "segments": [
        {
          "type": "hymnal",
          "text": "May the king desire you in your beauty; respect him, for he is your lord."
        }
      ],
      "footnotes": [],
      "references": []
    },
    {
      "verse_num": "12",
      "segments": [
        {
          "type": "hymnal",
          "text": "The people of Tyre will come with gifts; rich people will look for your favor."
        }
      ],
      "footnotes": [],
      "references": []
    },
    {
      "verse_num": "13",
      "segments": [
        {
          "type": "hymnal",
          "text": "Inside her preparation room the princess bride looks wonderful in her golden gown."
        }
      ],
      "footnotes": [],
      "references": []
    },
    {
      "verse_num": "14",
      "segments": [
        {
          "type": "hymnal",
          "text": "Wearing her beautiful clothes she is brought to the king, followed by her bridesmaids."
        }
      ],
      "footnotes": [],
      "references": []
    },
    {
      "verse_num": "15",
      "segments": [
        {
          "type": "hymnal",
          "text": "What a happy, joyful procession enters the king's palace!"
        }
      ],
      "footnotes": [],
      "references": []
    },
    {
      "verse_num": "16",
      "segments": [
        {
          "type": "hymnal",
          "text": "Your sons will take the place of your fathers; as princes you will make them rulers throughout the land."
        }
      ],
      "footnotes": [],
      "references": []
    },
    {
      "verse_num": "17",
      "segments": [
        {
          "type": "hymnal",
          "text": "Through my words you will be famous through all generations, and nations will praise you forever and ever."
        }
      ],
      "footnotes": [],
      "references": []
    }
  ]
}